{"provider":"https://www.exchangerate-api.com","WARNING_UPGRADE_TO_V6":"https://www.exchangerate-api.com/docs/free","terms":"https://www.exchangerate-api.com/terms","base":"USD","date":"2025-06-24","time_last_updated":1750723202,"rates":{"USD":1,"AED":3.67,"AFN":71.06,"ALL":85.29,"AMD":385.75,"ANG":1.79,"AOA":920.31,"ARS":1167.33,"AUD":1.55,"AWG":1.79,"AZN":1.7,"BAM":1.69,"BBD":2,"BDT":122.28,"BGN":1.69,"BHD":0.376,"BIF":2973.63,"BMD":1,"BND":1.29,"BOB":6.93,"BRL":5.51,"BSD":1,"BTN":86.63,"BWP":13.48,"BYN":3.15,"BZD":2,"CAD":1.37,"CDF":2881.9,"CHF":0.815,"CLP":941.55,"CNY":7.18,"COP":4083.57,"CRC":505.32,"CUP":24,"CVE":95.49,"CZK":21.54,"DJF":177.72,"DKK":6.45,"DOP":59.38,"DZD":130.31,"EGP":50.68,"ERN":15,"ETB":135.2,"EUR":0.866,"FJD":2.27,"FKP":0.741,"FOK":6.44,"GBP":0.741,"GEL":2.73,"GGP":0.741,"GHS":10.55,"GIP":0.741,"GMD":72.74,"GNF":8699.11,"GTQ":7.69,"GYD":209.19,"HKD":7.85,"HNL":26.13,"HRK":6.52,"HTG":131.22,"HUF":349.59,"IDR":16497.82,"ILS":3.45,"IMP":0.741,"INR":86.63,"IQD":1308.88,"IRR":42481.33,"ISK":124.55,"JEP":0.741,"JMD":159.78,"JOD":0.709,"JPY":146.34,"KES":129.24,"KGS":87.33,"KHR":4028.73,"KID":1.55,"KMF":426.05,"KRW":1378.27,"KWD":0.306,"KYD":0.833,"KZT":521.96,"LAK":21701.32,"LBP":89500,"LKR":300.64,"LRD":200.08,"LSL":17.93,"LYD":5.45,"MAD":9.14,"MDL":17.18,"MGA":4432.96,"MKD":53.44,"MMK":2098.6,"MNT":3604.94,"MOP":8.09,"MRU":39.71,"MUR":45.66,"MVR":15.45,"MWK":1741.85,"MXN":19.16,"MYR":4.29,"MZN":63.63,"NAD":17.93,"NGN":1549.49,"NIO":36.81,"NOK":10.1,"NPR":138.6,"NZD":1.68,"OMR":0.384,"PAB":1,"PEN":3.6,"PGK":4.14,"PHP":57.49,"PKR":283.8,"PLN":3.71,"PYG":8012.51,"QAR":3.64,"RON":4.39,"RSD":102.15,"RUB":78.44,"RWF":1447.44,"SAR":3.75,"SBD":8.55,"SCR":14.51,"SDG":454.1,"SEK":9.64,"SGD":1.29,"SHP":0.741,"SLE":22.47,"SLL":22466.28,"SOS":571.39,"SRD":38.82,"SSP":4707.86,"STN":21.22,"SYP":12916.62,"SZL":17.93,"THB":32.85,"TJS":9.88,"TMT":3.5,"TND":2.93,"TOP":2.39,"TRY":39.71,"TTD":6.8,"TVD":1.55,"TWD":29.6,"TZS":2627.71,"UAH":41.89,"UGX":3604.67,"UYU":40.96,"UZS":12372.51,"VES":105.45,"VND":26123.21,"VUV":119.24,"WST":2.69,"XAF":568.06,"XCD":2.7,"XCG":1.79,"XDR":0.735,"XOF":568.06,"XPF":103.34,"YER":242.7,"ZAR":17.93,"ZMW":23.22,"ZWL":27}}